Shamir/__init__.py
Shamir/shamir.py
shamir_lbodlev-0.2.2.dist-info/licenses/LICENSE
shamir_lbodlev-0.2.2.dist-info/METADATA
shamir_lbodlev-0.2.2.dist-info/WHEEL
shamir_lbodlev-0.2.2.dist-info/top_level.txt
shamir_lbodlev-0.2.2.dist-info/RECORD
