Metadata-Version: 2.4
Name: shamir-lbodlev
Version: 0.2.2
Summary: Simple implementation of Shamir's Secret Sharing scheme
Author-email: Bodlev Laurentiu <lbodlev888@gmail.com>
License: MIT
Project-URL: Homepage, https://github.com/lbodlev888/shamir
Project-URL: Repository, https://github.com/lbodlev888/shamir
Project-URL: Bug Tracker, https://github.com/lbodlev888/shamir/issues
Keywords: shamir,implementation,secret-sharing
Classifier: Programming Language :: Python :: 3
Classifier: License :: OSI Approved :: MIT License
Classifier: Operating System :: OS Independent
Requires-Python: >=3.8
License-File: LICENSE
Requires-Dist: pycryptodome>=3.23.0
Dynamic: license-file
